image_grouping_tool/__init__.py
image_grouping_tool/__main__.py
image_grouping_tool/dataset.py
image_grouping_tool/clustering/__init__.py
image_grouping_tool/clustering/db_scan.py
image_grouping_tool/clustering/distance_functions.py
image_grouping_tool/data_preparation/__init__.py
image_grouping_tool/data_preparation/pca.py
image_grouping_tool/data_preparation/plot.py
image_grouping_tool/image_descriptors/__init__.py
image_grouping_tool/image_descriptors/efficientnet_v2.py
image_grouping_tool/image_descriptors/factory.py
image_grouping_tool/image_descriptors/resnet.py
image_grouping_tool-0.1.3.dist-info/METADATA
image_grouping_tool-0.1.3.dist-info/WHEEL
image_grouping_tool-0.1.3.dist-info/entry_points.txt
image_grouping_tool-0.1.3.dist-info/top_level.txt
image_grouping_tool-0.1.3.dist-info/RECORD
